undertst.py
tst/__init__.py
tst/colors.py
tst/jsonfile.py
tst/tst.py
tst/utils.py
tst/commands/__init__.py
tst/commands/dispatcher.py
tst/commands/test.py
tst/commands/version.py
tst-0.19.0.data/scripts/runjava
tst-0.19.0.dist-info/LICENSE
tst-0.19.0.dist-info/METADATA
tst-0.19.0.dist-info/WHEEL
tst-0.19.0.dist-info/entry_points.txt
tst-0.19.0.dist-info/top_level.txt
tst-0.19.0.dist-info/RECORD
