Metadata-Version: 2.1
Name: tst
Version: 0.19.0
Summary: TST Simple Test Runner
Home-page: http://github.com/daltonserey/tst
Author: Dalton Serey
Author-email: daltonserey@gmail.com
Maintainer: Dalton Serey
Maintainer-email: daltonserey@gmail.com
License: MIT
Platform: UNKNOWN
Requires-Python: >=3.8
License-File: LICENSE
Requires-Dist: pyyaml (>=5.4.1)
Requires-Dist: requests (>=2.6.1)
Requires-Dist: cachecontrol[filecache]
